clusterdock/__init__.py
clusterdock/cli.py
clusterdock/config.py
clusterdock/defaults.yaml
clusterdock/exceptions.py
clusterdock/models.py
clusterdock/utils.py
clusterdock/actions/__init__.py
clusterdock/actions/manage.py
clusterdock/actions/ssh.py
clusterdock-1.0.2.dist-info/DESCRIPTION.rst
clusterdock-1.0.2.dist-info/METADATA
clusterdock-1.0.2.dist-info/RECORD
clusterdock-1.0.2.dist-info/WHEEL
clusterdock-1.0.2.dist-info/entry_points.txt
clusterdock-1.0.2.dist-info/metadata.json
clusterdock-1.0.2.dist-info/top_level.txt
tests/__init__.py
tests/test_clusterdock.py
