Metadata-Version: 2.0
Name: clusterdock
Version: 1.0.2
Summary: clusterdock is a framework for creating Docker-based container clusters
Home-page: https://github.com/clusterdock/clusterdock
Author: Dima Spivak
Author-email: dima@spivak.ch
License: Apache Software License 2.0
Keywords: clusterdock
Platform: UNKNOWN
Classifier: Development Status :: 2 - Pre-Alpha
Classifier: Intended Audience :: Developers
Classifier: License :: OSI Approved :: Apache Software License
Classifier: Natural Language :: English
Classifier: Programming Language :: Python :: 3
Classifier: Programming Language :: Python :: 3.3
Classifier: Programming Language :: Python :: 3.4
Classifier: Programming Language :: Python :: 3.5
Requires-Dist: PyYAML
Requires-Dist: docker
Requires-Dist: requests
